README.txt
setup.cfg
setup.py
docs/HISTORY.txt
docs/INSTALL.txt
docs/LICENSE.GPL
docs/LICENSE.txt
unimr/__init__.py
unimr.compositeindex.egg-info/PKG-INFO
unimr.compositeindex.egg-info/SOURCES.txt
unimr.compositeindex.egg-info/dependency_links.txt
unimr.compositeindex.egg-info/entry_points.txt
unimr.compositeindex.egg-info/namespace_packages.txt
unimr.compositeindex.egg-info/not-zip-safe
unimr.compositeindex.egg-info/paster_plugins.txt
unimr.compositeindex.egg-info/requires.txt
unimr.compositeindex.egg-info/top_level.txt
unimr/compositeindex/CompositeIndex.py
unimr/compositeindex/__init__.py
unimr/compositeindex/catalog.py
unimr/compositeindex/config.py
unimr/compositeindex/configure.zcml
unimr/compositeindex/tests.py
unimr/compositeindex/util.py
unimr/compositeindex/wrapper.py
unimr/compositeindex/dtml/addCompositeIndex.dtml
unimr/compositeindex/dtml/browseIndex.dtml
unimr/compositeindex/dtml/manageCompositeIndex.dtml
unimr/compositeindex/help/CompositeIndex_searchResults.stx
unimr/compositeindex/www/index.gif