Metadata-Version: 1.0
Name: unimr.compositeindex
Version: 0.1dev-r84057
Summary: Composite index for the Catalog
Home-page: https://svn.plone.org/svn/collective/unimr.compositeindex
Author: Andreas Gabriel
Author-email: gabriel@hrz.uni-marburg.de
License: ZPL
Keywords: Catalog ZCatalog Composite Index
Platform: UNKNOWN
Classifier: Framework :: Plone
Classifier: Framework :: Zope2
Classifier: Programming Language :: Python
Classifier: Topic :: Software Development :: Libraries :: Python Modules
